{
    "info": {
        "name": "Gold Platform API",
        "description": "Complete API collection for Gold Platform with Reservation System",
        "version": "1.0.0",
        "schema": "https://schema.getpostman.com/json/collection/v2.1.0/collection.json"
    },
    "auth": {
        "type": "bearer",
        "bearer": [
            {
                "key": "token",
                "value": "{{auth_token}}",
                "type": "string"
            }
        ]
    },
    "variable": [
        {
            "key": "base_url",
            "value": "http://localhost:5000",
            "type": "string"
        },
        {
            "key": "auth_token",
            "value": "",
            "type": "string"
        },
        {
            "key": "user_id",
            "value": "",
            "type": "string"
        },
        {
            "key": "product_id",
            "value": "",
            "type": "string"
        },
        {
            "key": "shop_id",
            "value": "",
            "type": "string"
        },
        {
            "key": "reservation_id",
            "value": "",
            "type": "string"
        }
    ],
    "item": [
        {
            "name": "System",
            "item": [
                {
                    "name": "Health Check",
                    "request": {
                        "method": "GET",
                        "header": [],
                        "url": {
                            "raw": "{{base_url}}/health",
                            "host": [
                                "{{base_url}}"
                            ],
                            "path": [
                                "health"
                            ]
                        }
                    }
                }
            ]
        },
        {
            "name": "Authentication",
            "item": [
                {
                    "name": "Register User",
                    "event": [
                        {
                            "listen": "test",
                            "script": {
                                "exec": [
                                    "if (pm.response.code === 201) {",
                                    "    const response = pm.response.json();",
                                    "    if (response.token) {",
                                    "        pm.collectionVariables.set('auth_token', response.token);",
                                    "        pm.collectionVariables.set('user_id', response.data.user._id);",
                                    "    }",
                                    "}"
                                ]
                            }
                        }
                    ],
                    "request": {
                        "method": "POST",
                        "header": [
                            {
                                "key": "Content-Type",
                                "value": "application/json"
                            }
                        ],
                        "body": {
                            "mode": "raw",
                            "raw": "{\n  \"name\": \"Ahmed Hassan\",\n  \"email\": \"ahmed@example.com\",\n  \"password\": \"password123\",\n  \"role\": \"customer\",\n  \"phone\": \"+201234567890\"\n}"
                        },
                        "url": {
                            "raw": "{{base_url}}/auth/register",
                            "host": [
                                "{{base_url}}"
                            ],
                            "path": [
                                "auth",
                                "register"
                            ]
                        }
                    }
                },
                {
                    "name": "Login User",
                    "event": [
                        {
                            "listen": "test",
                            "script": {
                                "exec": [
                                    "if (pm.response.code === 200) {",
                                    "    const response = pm.response.json();",
                                    "    if (response.token) {",
                                    "        pm.collectionVariables.set('auth_token', response.token);",
                                    "        pm.collectionVariables.set('user_id', response.data.user._id);",
                                    "    }",
                                    "}"
                                ]
                            }
                        }
                    ],
                    "request": {
                        "method": "POST",
                        "header": [
                            {
                                "key": "Content-Type",
                                "value": "application/json"
                            }
                        ],
                        "body": {
                            "mode": "raw",
                            "raw": "{\n  \"email\": \"ahmed@example.com\",\n  \"password\": \"password123\"\n}"
                        },
                        "url": {
                            "raw": "{{base_url}}/auth/login",
                            "host": [
                                "{{base_url}}"
                            ],
                            "path": [
                                "auth",
                                "login"
                            ]
                        }
                    }
                },
                {
                    "name": "Google OAuth",
                    "request": {
                        "method": "GET",
                        "header": [],
                        "url": {
                            "raw": "{{base_url}}/auth/google",
                            "host": [
                                "{{base_url}}"
                            ],
                            "path": [
                                "auth",
                                "google"
                            ]
                        }
                    }
                }
            ]
        },
        {
            "name": "Users",
            "item": [
                {
                    "name": "Get User Profile",
                    "request": {
                        "method": "GET",
                        "header": [
                            {
                                "key": "Authorization",
                                "value": "Bearer {{auth_token}}"
                            }
                        ],
                        "url": {
                            "raw": "{{base_url}}/user/profile",
                            "host": [
                                "{{base_url}}"
                            ],
                            "path": [
                                "user",
                                "profile"
                            ]
                        }
                    }
                },
                {
                    "name": "Update User Profile",
                    "request": {
                        "method": "PUT",
                        "header": [
                            {
                                "key": "Authorization",
                                "value": "Bearer {{auth_token}}"
                            },
                            {
                                "key": "Content-Type",
                                "value": "application/json"
                            }
                        ],
                        "body": {
                            "mode": "raw",
                            "raw": "{\n  \"name\": \"Ahmed Hassan Updated\",\n  \"phone\": \"+201234567890\",\n  \"address\": \"123 Street, Cairo\"\n}"
                        },
                        "url": {
                            "raw": "{{base_url}}/user/profile",
                            "host": [
                                "{{base_url}}"
                            ],
                            "path": [
                                "user",
                                "profile"
                            ]
                        }
                    }
                },
                {
                    "name": "Change Password",
                    "request": {
                        "method": "POST",
                        "header": [
                            {
                                "key": "Authorization",
                                "value": "Bearer {{auth_token}}"
                            },
                            {
                                "key": "Content-Type",
                                "value": "application/json"
                            }
                        ],
                        "body": {
                            "mode": "raw",
                            "raw": "{\n  \"currentPassword\": \"password123\",\n  \"newPassword\": \"newpassword456\"\n}"
                        },
                        "url": {
                            "raw": "{{base_url}}/user/change-password",
                            "host": [
                                "{{base_url}}"
                            ],
                            "path": [
                                "user",
                                "change-password"
                            ]
                        }
                    }
                }
            ]
        },
        {
            "name": "Shops",
            "item": [
                {
                    "name": "Get All Shops",
                    "request": {
                        "method": "GET",
                        "header": [],
                        "url": {
                            "raw": "{{base_url}}/shop?city=Cairo&approved=true",
                            "host": [
                                "{{base_url}}"
                            ],
                            "path": [
                                "shop"
                            ],
                            "query": [
                                {
                                    "key": "city",
                                    "value": "Cairo"
                                },
                                {
                                    "key": "approved",
                                    "value": "true"
                                }
                            ]
                        }
                    }
                },
                {
                    "name": "Create Shop",
                    "event": [
                        {
                            "listen": "test",
                            "script": {
                                "exec": [
                                    "if (pm.response.code === 201) {",
                                    "    const response = pm.response.json();",
                                    "    if (response.data && response.data._id) {",
                                    "        pm.collectionVariables.set('shop_id', response.data._id);",
                                    "    }",
                                    "}"
                                ]
                            }
                        }
                    ],
                    "request": {
                        "method": "POST",
                        "header": [
                            {
                                "key": "Authorization",
                                "value": "Bearer {{auth_token}}"
                            }
                        ],
                        "body": {
                            "mode": "formdata",
                            "formdata": [
                                {
                                    "key": "name",
                                    "value": "Golden Dreams Jewelry",
                                    "type": "text"
                                },
                                {
                                    "key": "description",
                                    "value": "Premium gold jewelry shop",
                                    "type": "text"
                                },
                                {
                                    "key": "address",
                                    "value": "123 Gold Street, Cairo",
                                    "type": "text"
                                },
                                {
                                    "key": "city",
                                    "value": "Cairo",
                                    "type": "text"
                                },
                                {
                                    "key": "phone",
                                    "value": "+201234567890",
                                    "type": "text"
                                }
                            ]
                        },
                        "url": {
                            "raw": "{{base_url}}/shop",
                            "host": [
                                "{{base_url}}"
                            ],
                            "path": [
                                "shop"
                            ]
                        }
                    }
                },
                {
                    "name": "Get Shop by ID",
                    "request": {
                        "method": "GET",
                        "header": [],
                        "url": {
                            "raw": "{{base_url}}/shop/{{shop_id}}",
                            "host": [
                                "{{base_url}}"
                            ],
                            "path": [
                                "shop",
                                "{{shop_id}}"
                            ]
                        }
                    }
                },
                {
                    "name": "Get Shop Products",
                    "request": {
                        "method": "GET",
                        "header": [],
                        "url": {
                            "raw": "{{base_url}}/shop/{{shop_id}}/products",
                            "host": [
                                "{{base_url}}"
                            ],
                            "path": [
                                "shop",
                                "{{shop_id}}",
                                "products"
                            ]
                        }
                    }
                }
            ]
        },
        {
            "name": "Products",
            "item": [
                {
                    "name": "Get All Products",
                    "request": {
                        "method": "GET",
                        "header": [
                            {
                                "key": "Authorization",
                                "value": "Bearer {{auth_token}}"
                            }
                        ],
                        "url": {
                            "raw": "{{base_url}}/product?category=necklaces&minPrice=1000&maxPrice=10000&karat=18&sortBy=price_low&search=gold",
                            "host": [
                                "{{base_url}}"
                            ],
                            "path": [
                                "product"
                            ],
                            "query": [
                                {
                                    "key": "category",
                                    "value": "necklaces"
                                },
                                {
                                    "key": "minPrice",
                                    "value": "1000"
                                },
                                {
                                    "key": "maxPrice",
                                    "value": "10000"
                                },
                                {
                                    "key": "karat",
                                    "value": "18"
                                },
                                {
                                    "key": "sortBy",
                                    "value": "price_low"
                                },
                                {
                                    "key": "search",
                                    "value": "gold"
                                }
                            ]
                        }
                    }
                },
                {
                    "name": "Create Product",
                    "event": [
                        {
                            "listen": "test",
                            "script": {
                                "exec": [
                                    "if (pm.response.code === 201) {",
                                    "    const response = pm.response.json();",
                                    "    if (response.data && response.data._id) {",
                                    "        pm.collectionVariables.set('product_id', response.data._id);",
                                    "    }",
                                    "}"
                                ]
                            }
                        }
                    ],
                    "request": {
                        "method": "POST",
                        "header": [
                            {
                                "key": "Authorization",
                                "value": "Bearer {{auth_token}}"
                            }
                        ],
                        "body": {
                            "mode": "formdata",
                            "formdata": [
                                {
                                    "key": "title",
                                    "value": "Gold Necklace 18K",
                                    "type": "text"
                                },
                                {
                                    "key": "description",
                                    "value": "Beautiful handcrafted gold necklace",
                                    "type": "text"
                                },
                                {
                                    "key": "karat",
                                    "value": "18",
                                    "type": "text"
                                },
                                {
                                    "key": "weight",
                                    "value": "25.5",
                                    "type": "text"
                                },
                                {
                                    "key": "design_type",
                                    "value": "necklaces",
                                    "type": "text"
                                },
                                {
                                    "key": "shop",
                                    "value": "{{shop_id}}",
                                    "type": "text"
                                }
                            ]
                        },
                        "url": {
                            "raw": "{{base_url}}/product",
                            "host": [
                                "{{base_url}}"
                            ],
                            "path": [
                                "product"
                            ]
                        }
                    }
                },
                {
                    "name": "Get Product by ID",
                    "request": {
                        "method": "GET",
                        "header": [
                            {
                                "key": "Authorization",
                                "value": "Bearer {{auth_token}}"
                            }
                        ],
                        "url": {
                            "raw": "{{base_url}}/product/{{product_id}}",
                            "host": [
                                "{{base_url}}"
                            ],
                            "path": [
                                "product",
                                "{{product_id}}"
                            ]
                        }
                    }
                },
                {
                    "name": "Update Product",
                    "request": {
                        "method": "PUT",
                        "header": [
                            {
                                "key": "Authorization",
                                "value": "Bearer {{auth_token}}"
                            },
                            {
                                "key": "Content-Type",
                                "value": "application/json"
                            }
                        ],
                        "body": {
                            "mode": "raw",
                            "raw": "{\n  \"title\": \"Updated Gold Necklace 18K\",\n  \"description\": \"Updated beautiful handcrafted gold necklace\",\n  \"karat\": 18,\n  \"weight\": 26.0\n}"
                        },
                        "url": {
                            "raw": "{{base_url}}/product/{{product_id}}",
                            "host": [
                                "{{base_url}}"
                            ],
                            "path": [
                                "product",
                                "{{product_id}}"
                            ]
                        }
                    }
                },
                {
                    "name": "Delete Product",
                    "request": {
                        "method": "DELETE",
                        "header": [
                            {
                                "key": "Authorization",
                                "value": "Bearer {{auth_token}}"
                            }
                        ],
                        "url": {
                            "raw": "{{base_url}}/product/{{product_id}}",
                            "host": [
                                "{{base_url}}"
                            ],
                            "path": [
                                "product",
                                "{{product_id}}"
                            ]
                        }
                    }
                },
                {
                    "name": "Toggle Favorite",
                    "request": {
                        "method": "POST",
                        "header": [
                            {
                                "key": "Authorization",
                                "value": "Bearer {{auth_token}}"
                            }
                        ],
                        "url": {
                            "raw": "{{base_url}}/product/{{product_id}}/favorite",
                            "host": [
                                "{{base_url}}"
                            ],
                            "path": [
                                "product",
                                "{{product_id}}",
                                "favorite"
                            ]
                        }
                    }
                },
                {
                    "name": "Get User Favorites",
                    "request": {
                        "method": "GET",
                        "header": [
                            {
                                "key": "Authorization",
                                "value": "Bearer {{auth_token}}"
                            }
                        ],
                        "url": {
                            "raw": "{{base_url}}/product/favorites/{{user_id}}",
                            "host": [
                                "{{base_url}}"
                            ],
                            "path": [
                                "product",
                                "favorites",
                                "{{user_id}}"
                            ]
                        }
                    }
                },
                {
                    "name": "Generate Description Variations",
                    "request": {
                        "method": "POST",
                        "header": [
                            {
                                "key": "Authorization",
                                "value": "Bearer {{auth_token}}"
                            }
                        ],
                        "url": {
                            "raw": "{{base_url}}/product/{{product_id}}/description-variations",
                            "host": [
                                "{{base_url}}"
                            ],
                            "path": [
                                "product",
                                "{{product_id}}",
                                "description-variations"
                            ]
                        }
                    }
                },
                {
                    "name": "Regenerate Description",
                    "request": {
                        "method": "POST",
                        "header": [
                            {
                                "key": "Authorization",
                                "value": "Bearer {{auth_token}}"
                            }
                        ],
                        "url": {
                            "raw": "{{base_url}}/product/{{product_id}}/regenerate-description",
                            "host": [
                                "{{base_url}}"
                            ],
                            "path": [
                                "product",
                                "{{product_id}}",
                                "regenerate-description"
                            ]
                        }
                    }
                },
                {
                    "name": "Track Product Click",
                    "request": {
                        "method": "POST",
                        "header": [
                            {
                                "key": "Authorization",
                                "value": "Bearer {{auth_token}}"
                            },
                            {
                                "key": "Content-Type",
                                "value": "application/json"
                            }
                        ],
                        "body": {
                            "mode": "raw",
                            "raw": "{\n  \"productId\": \"{{product_id}}\"\n}"
                        },
                        "url": {
                            "raw": "{{base_url}}/product/track-click",
                            "host": [
                                "{{base_url}}"
                            ],
                            "path": [
                                "product",
                                "track-click"
                            ]
                        }
                    }
                },
                {
                    "name": "Get Related Products",
                    "request": {
                        "method": "GET",
                        "header": [
                            {
                                "key": "Authorization",
                                "value": "Bearer {{auth_token}}"
                            }
                        ],
                        "url": {
                            "raw": "{{base_url}}/product/related?limit=8",
                            "host": [
                                "{{base_url}}"
                            ],
                            "path": [
                                "product",
                                "related"
                            ],
                            "query": [
                                {
                                    "key": "limit",
                                    "value": "8"
                                }
                            ]
                        }
                    }
                }
            ]
        },
        {
            "name": "Reservations",
            "item": [
                {
                    "name": "Create Reservation",
                    "event": [
                        {
                            "listen": "test",
                            "script": {
                                "exec": [
                                    "if (pm.response.code === 201) {",
                                    "    const response = pm.response.json();",
                                    "    if (response.data && response.data.reservation && response.data.reservation._id) {",
                                    "        pm.collectionVariables.set('reservation_id', response.data.reservation._id);",
                                    "    }",
                                    "}"
                                ]
                            }
                        }
                    ],
                    "request": {
                        "method": "POST",
                        "header": [
                            {
                                "key": "Authorization",
                                "value": "Bearer {{auth_token}}"
                            },
                            {
                                "key": "Content-Type",
                                "value": "application/json"
                            }
                        ],
                        "body": {
                            "mode": "raw",
                            "raw": "{\n  \"productId\": \"{{product_id}}\",\n  \"paymentMethodId\": \"pm_card_visa\"\n}"
                        },
                        "url": {
                            "raw": "{{base_url}}/reservations",
                            "host": [
                                "{{base_url}}"
                            ],
                            "path": [
                                "reservations"
                            ]
                        }
                    }
                },
                {
                    "name": "Get User Reservations",
                    "request": {
                        "method": "GET",
                        "header": [
                            {
                                "key": "Authorization",
                                "value": "Bearer {{auth_token}}"
                            }
                        ],
                        "url": {
                            "raw": "{{base_url}}/reservations?status=ACTIVE&page=1&limit=10",
                            "host": [
                                "{{base_url}}"
                            ],
                            "path": [
                                "reservations"
                            ],
                            "query": [
                                {
                                    "key": "status",
                                    "value": "ACTIVE"
                                },
                                {
                                    "key": "page",
                                    "value": "1"
                                },
                                {
                                    "key": "limit",
                                    "value": "10"
                                }
                            ]
                        }
                    }
                },
                {
                    "name": "Get Reservation Details",
                    "request": {
                        "method": "GET",
                        "header": [
                            {
                                "key": "Authorization",
                                "value": "Bearer {{auth_token}}"
                            }
                        ],
                        "url": {
                            "raw": "{{base_url}}/reservations/{{reservation_id}}",
                            "host": [
                                "{{base_url}}"
                            ],
                            "path": [
                                "reservations",
                                "{{reservation_id}}"
                            ]
                        }
                    }
                },
                {
                    "name": "Confirm Reservation",
                    "request": {
                        "method": "POST",
                        "header": [
                            {
                                "key": "Authorization",
                                "value": "Bearer {{auth_token}}"
                            },
                            {
                                "key": "Content-Type",
                                "value": "application/json"
                            }
                        ],
                        "body": {
                            "mode": "raw",
                            "raw": "{\n  \"paymentMethodId\": \"pm_card_visa\"\n}"
                        },
                        "url": {
                            "raw": "{{base_url}}/reservations/{{reservation_id}}/confirm",
                            "host": [
                                "{{base_url}}"
                            ],
                            "path": [
                                "reservations",
                                "{{reservation_id}}",
                                "confirm"
                            ]
                        }
                    }
                },
                {
                    "name": "Cancel Reservation",
                    "request": {
                        "method": "DELETE",
                        "header": [
                            {
                                "key": "Authorization",
                                "value": "Bearer {{auth_token}}"
                            },
                            {
                                "key": "Content-Type",
                                "value": "application/json"
                            }
                        ],
                        "body": {
                            "mode": "raw",
                            "raw": "{\n  \"reason\": \"Customer changed mind\"\n}"
                        },
                        "url": {
                            "raw": "{{base_url}}/reservations/{{reservation_id}}",
                            "host": [
                                "{{base_url}}"
                            ],
                            "path": [
                                "reservations",
                                "{{reservation_id}}"
                            ]
                        }
                    }
                },
                {
                    "name": "Get Shop Reservations",
                    "request": {
                        "method": "GET",
                        "header": [
                            {
                                "key": "Authorization",
                                "value": "Bearer {{auth_token}}"
                            }
                        ],
                        "url": {
                            "raw": "{{base_url}}/reservations/shop/{{shop_id}}?status=ACTIVE",
                            "host": [
                                "{{base_url}}"
                            ],
                            "path": [
                                "reservations",
                                "shop",
                                "{{shop_id}}"
                            ],
                            "query": [
                                {
                                    "key": "status",
                                    "value": "ACTIVE"
                                }
                            ]
                        }
                    }
                },
                {
                    "name": "Update Reservation Status",
                    "request": {
                        "method": "PATCH",
                        "header": [
                            {
                                "key": "Authorization",
                                "value": "Bearer {{auth_token}}"
                            },
                            {
                                "key": "Content-Type",
                                "value": "application/json"
                            }
                        ],
                        "body": {
                            "mode": "raw",
                            "raw": "{\n  \"status\": \"READY_FOR_PICKUP\",\n  \"notes\": \"Product is ready for customer pickup\"\n}"
                        },
                        "url": {
                            "raw": "{{base_url}}/reservations/{{reservation_id}}/status",
                            "host": [
                                "{{base_url}}"
                            ],
                            "path": [
                                "reservations",
                                "{{reservation_id}}",
                                "status"
                            ]
                        }
                    }
                }
            ]
        },
        {
            "name": "Bookings",
            "item": [
                {
                    "name": "Create Booking",
                    "request": {
                        "method": "POST",
                        "header": [
                            {
                                "key": "Authorization",
                                "value": "Bearer {{auth_token}}"
                            },
                            {
                                "key": "Content-Type",
                                "value": "application/json"
                            }
                        ],
                        "body": {
                            "mode": "raw",
                            "raw": "{\n  \"shopId\": \"{{shop_id}}\",\n  \"appointmentDate\": \"2024-01-15T10:30:00.000Z\",\n  \"notes\": \"Looking for wedding rings\"\n}"
                        },
                        "url": {
                            "raw": "{{base_url}}/booking",
                            "host": [
                                "{{base_url}}"
                            ],
                            "path": [
                                "booking"
                            ]
                        }
                    }
                },
                {
                    "name": "Get User Bookings",
                    "request": {
                        "method": "GET",
                        "header": [
                            {
                                "key": "Authorization",
                                "value": "Bearer {{auth_token}}"
                            }
                        ],
                        "url": {
                            "raw": "{{base_url}}/booking?status=pending",
                            "host": [
                                "{{base_url}}"
                            ],
                            "path": [
                                "booking"
                            ],
                            "query": [
                                {
                                    "key": "status",
                                    "value": "pending"
                                }
                            ]
                        }
                    }
                },
                {
                    "name": "Update Booking Status",
                    "request": {
                        "method": "PUT",
                        "header": [
                            {
                                "key": "Authorization",
                                "value": "Bearer {{auth_token}}"
                            },
                            {
                                "key": "Content-Type",
                                "value": "application/json"
                            }
                        ],
                        "body": {
                            "mode": "raw",
                            "raw": "{\n  \"status\": \"confirmed\",\n  \"notes\": \"Appointment confirmed for tomorrow\"\n}"
                        },
                        "url": {
                            "raw": "{{base_url}}/booking/booking_id_here",
                            "host": [
                                "{{base_url}}"
                            ],
                            "path": [
                                "booking",
                                "booking_id_here"
                            ]
                        }
                    }
                }
            ]
        },
        {
            "name": "Ratings",
            "item": [
                {
                    "name": "Rate Shop",
                    "request": {
                        "method": "POST",
                        "header": [
                            {
                                "key": "Authorization",
                                "value": "Bearer {{auth_token}}"
                            },
                            {
                                "key": "Content-Type",
                                "value": "application/json"
                            }
                        ],
                        "body": {
                            "mode": "raw",
                            "raw": "{\n  \"shopId\": \"{{shop_id}}\",\n  \"rating\": 4.5,\n  \"comment\": \"Excellent service and beautiful jewelry\"\n}"
                        },
                        "url": {
                            "raw": "{{base_url}}/rate",
                            "host": [
                                "{{base_url}}"
                            ],
                            "path": [
                                "rate"
                            ]
                        }
                    }
                },
                {
                    "name": "Get Shop Ratings",
                    "request": {
                        "method": "GET",
                        "header": [],
                        "url": {
                            "raw": "{{base_url}}/rate/{{shop_id}}",
                            "host": [
                                "{{base_url}}"
                            ],
                            "path": [
                                "rate",
                                "{{shop_id}}"
                            ]
                        }
                    }
                }
            ]
        },
        {
            "name": "Price Calculation",
            "item": [
                {
                    "name": "Calculate Gold Price",
                    "request": {
                        "method": "POST",
                        "header": [
                            {
                                "key": "Content-Type",
                                "value": "application/json"
                            }
                        ],
                        "body": {
                            "mode": "raw",
                            "raw": "{\n  \"karat\": 18,\n  \"weight\": 25.5,\n  \"makingChargePercentage\": 15\n}"
                        },
                        "url": {
                            "raw": "{{base_url}}/price/calculate",
                            "host": [
                                "{{base_url}}"
                            ],
                            "path": [
                                "price",
                                "calculate"
                            ]
                        }
                    }
                },
                {
                    "name": "Get Current Gold Prices",
                    "request": {
                        "method": "GET",
                        "header": [],
                        "url": {
                            "raw": "{{base_url}}/price/current",
                            "host": [
                                "{{base_url}}"
                            ],
                            "path": [
                                "price",
                                "current"
                            ]
                        }
                    }
                }
            ]
        },
        {
            "name": "Notifications",
            "item": [
                {
                    "name": "Get User Notifications",
                    "request": {
                        "method": "GET",
                        "header": [
                            {
                                "key": "Authorization",
                                "value": "Bearer {{auth_token}}"
                            }
                        ],
                        "url": {
                            "raw": "{{base_url}}/notifications?unread=true&page=1&limit=20",
                            "host": [
                                "{{base_url}}"
                            ],
                            "path": [
                                "notifications"
                            ],
                            "query": [
                                {
                                    "key": "unread",
                                    "value": "true"
                                },
                                {
                                    "key": "page",
                                    "value": "1"
                                },
                                {
                                    "key": "limit",
                                    "value": "20"
                                }
                            ]
                        }
                    }
                },
                {
                    "name": "Mark Notification as Read",
                    "request": {
                        "method": "PATCH",
                        "header": [
                            {
                                "key": "Authorization",
                                "value": "Bearer {{auth_token}}"
                            }
                        ],
                        "url": {
                            "raw": "{{base_url}}/notifications/notification_id_here/read",
                            "host": [
                                "{{base_url}}"
                            ],
                            "path": [
                                "notifications",
                                "notification_id_here",
                                "read"
                            ]
                        }
                    }
                },
                {
                    "name": "Mark All Notifications as Read",
                    "request": {
                        "method": "PATCH",
                        "header": [
                            {
                                "key": "Authorization",
                                "value": "Bearer {{auth_token}}"
                            }
                        ],
                        "url": {
                            "raw": "{{base_url}}/notifications/mark-all-read",
                            "host": [
                                "{{base_url}}"
                            ],
                            "path": [
                                "notifications",
                                "mark-all-read"
                            ]
                        }
                    }
                }
            ]
        },
        {
            "name": "Dashboard",
            "item": [
                {
                    "name": "Get Dashboard Stats",
                    "request": {
                        "method": "GET",
                        "header": [
                            {
                                "key": "Authorization",
                                "value": "Bearer {{auth_token}}"
                            }
                        ],
                        "url": {
                            "raw": "{{base_url}}/dashboard/stats",
                            "host": [
                                "{{base_url}}"
                            ],
                            "path": [
                                "dashboard",
                                "stats"
                            ]
                        }
                    }
                },
                {
                    "name": "Get Shop Statistics",
                    "request": {
                        "method": "GET",
                        "header": [
                            {
                                "key": "Authorization",
                                "value": "Bearer {{auth_token}}"
                            }
                        ],
                        "url": {
                            "raw": "{{base_url}}/dashboard/shop/{{shop_id}}/stats",
                            "host": [
                                "{{base_url}}"
                            ],
                            "path": [
                                "dashboard",
                                "shop",
                                "{{shop_id}}",
                                "stats"
                            ]
                        }
                    }
                }
            ]
        },
        {
            "name": "Chatbot",
            "item": [
                {
                    "name": "Send Message to Chatbot",
                    "request": {
                        "method": "POST",
                        "header": [
                            {
                                "key": "Content-Type",
                                "value": "application/json"
                            }
                        ],
                        "body": {
                            "mode": "raw",
                            "raw": "{\n  \"message\": \"I'm looking for gold necklaces\",\n  \"sessionId\": \"session_12345\"\n}"
                        },
                        "url": {
                            "raw": "{{base_url}}/chatbot/chat",
                            "host": [
                                "{{base_url}}"
                            ],
                            "path": [
                                "chatbot",
                                "chat"
                            ]
                        }
                    }
                }
            ]
        },
        {
            "name": "Webhooks",
            "item": [
                {
                    "name": "Stripe Webhook",
                    "request": {
                        "method": "POST",
                        "header": [
                            {
                                "key": "Content-Type",
                                "value": "application/json"
                            },
                            {
                                "key": "stripe-signature",
                                "value": "webhook_signature_here"
                            }
                        ],
                        "body": {
                            "mode": "raw",
                            "raw": "{\n  \"id\": \"evt_1234567890\",\n  \"object\": \"event\",\n  \"type\": \"payment_intent.succeeded\",\n  \"data\": {\n    \"object\": {\n      \"id\": \"pi_1234567890\",\n      \"metadata\": {\n        \"type\": \"reservation\",\n        \"userId\": \"{{user_id}}\",\n        \"productId\": \"{{product_id}}\"\n      }\n    }\n  }\n}"
                        },
                        "url": {
                            "raw": "{{base_url}}/webhooks/stripe",
                            "host": [
                                "{{base_url}}"
                            ],
                            "path": [
                                "webhooks",
                                "stripe"
                            ]
                        }
                    }
                }
            ]
        },
        {
            "name": "Testing & Development",
            "item": [
                {
                    "name": "Test Reservation System",
                    "request": {
                        "method": "GET",
                        "header": [
                            {
                                "key": "Authorization",
                                "value": "Bearer {{auth_token}}"
                            }
                        ],
                        "url": {
                            "raw": "{{base_url}}/test/reservation",
                            "host": [
                                "{{base_url}}"
                            ],
                            "path": [
                                "test",
                                "reservation"
                            ]
                        }
                    }
                },
                {
                    "name": "Get Server Info",
                    "request": {
                        "method": "GET",
                        "header": [],
                        "url": {
                            "raw": "{{base_url}}/",
                            "host": [
                                "{{base_url}}"
                            ],
                            "path": [
                                ""
                            ]
                        }
                    }
                }
            ]
        }
    ],
    "event": [
        {
            "listen": "prerequest",
            "script": {
                "type": "text/javascript",
                "exec": [
                    "// Global pre-request script",
                    "console.log('Making request to:', pm.request.url);",
                    "",
                    "// Set default content type if not set",
                    "if (pm.request.method !== 'GET' && !pm.request.headers.has('Content-Type')) {",
                    "    pm.request.headers.add({key: 'Content-Type', value: 'application/json'});",
                    "}"
                ]
            }
        },
        {
            "listen": "test",
            "script": {
                "type": "text/javascript",
                "exec": [
                    "// Global test script",
                    "pm.test('Status code should be success', function () {",
                    "    pm.expect(pm.response.code).to.be.oneOf([200, 201, 202, 204]);",
                    "});",
                    "",
                    "pm.test('Response should be JSON', function () {",
                    "    pm.expect(pm.response.headers.get('Content-Type')).to.include('application/json');",
                    "});",
                    "",
                    "// Log response for debugging",
                    "console.log('Response Status:', pm.response.code);",
                    "console.log('Response Time:', pm.response.responseTime + 'ms');"
                ]
            }
        }
    ]
}